{
  "id": "meta-hybrid_mount",
  "timestamp": 1768665482.0,
  "versions": [
    {
      "timestamp": 1770808060.0,
      "version": "3.0.14-1176",
      "versionCode": 148,
      "zipUrl": "https://rooting.unatried.com/modules/meta-hybrid_mount/3.0.14-1176_148.zip",
      "changelog": "https://rooting.unatried.com/modules/meta-hybrid_mount/3.0.14-1176_148.md",
      "size": 3994478
    },
    {
      "timestamp": 1770826060.0,
      "version": "3.0.2-1180",
      "versionCode": 149,
      "zipUrl": "https://rooting.unatried.com/modules/meta-hybrid_mount/3.0.2-1180_149.zip",
      "changelog": "https://rooting.unatried.com/modules/meta-hybrid_mount/3.0.2-1180_149.md",
      "size": 3994851
    },
    {
      "timestamp": 1771394642.0,
      "version": "3.1.0-1222",
      "versionCode": 30100,
      "zipUrl": "https://rooting.unatried.com/modules/meta-hybrid_mount/3.1.0-1222_30100.zip",
      "changelog": "https://rooting.unatried.com/modules/meta-hybrid_mount/3.1.0-1222_30100.md",
      "size": 3913878
    }
  ]
}